tests/__init__.py
tests/models.py
tests/test_models.py
tests/test_utils.py
django_materialized_paths-0.1.dist-info/LICENSE.md
django_materialized_paths-0.1.dist-info/METADATA
django_materialized_paths-0.1.dist-info/WHEEL
django_materialized_paths-0.1.dist-info/top_level.txt
django_materialized_paths-0.1.dist-info/RECORD
