Metadata-Version: 2.1
Name: django-materialized-paths
Version: 0.1
Summary: A simple and lightweight implementation of materialized path tree structures in Django.
Home-page: https://github.com/cmcnierney/django-materialized-paths
Author: Cameron McNierney
Author-email: cameron.mcnierney@gmail.com
License: MIT License
Platform: UNKNOWN
Classifier: Environment :: Web Environment
Classifier: Framework :: Django
Classifier: Framework :: Django :: 2.2
Classifier: Intended Audience :: Developers
Classifier: License :: OSI Approved :: MIT License
Classifier: Operating System :: OS Independent
Classifier: Programming Language :: Python
Classifier: Programming Language :: Python :: 3
Classifier: Topic :: Internet :: WWW/HTTP
Classifier: Topic :: Internet :: WWW/HTTP :: Dynamic Content
